TurboTalk_WEBUI/__init__.py
TurboTalk_WEBUI/app.py
TurboTalk_WEBUI-0.1.5.dist-info/METADATA
TurboTalk_WEBUI-0.1.5.dist-info/WHEEL
TurboTalk_WEBUI-0.1.5.dist-info/entry_points.txt
TurboTalk_WEBUI-0.1.5.dist-info/top_level.txt
TurboTalk_WEBUI-0.1.5.dist-info/RECORD
