Metadata-Version: 2.1
Name: TurboTalk_WEBUI
Version: 0.1.5
Requires-Dist: Flask
Requires-Dist: g4f
